omero_biomero/__init__.py
omero_biomero/_version.py
omero_biomero/admin_views.py
omero_biomero/analyzer_views.py
omero_biomero/app.py
omero_biomero/biomero_views.py
omero_biomero/importer_views.py
omero_biomero/omero-biomero.omero
omero_biomero/settings.py
omero_biomero/setup_integration.py
omero_biomero/test_settings.py
omero_biomero/urls.py
omero_biomero/utils.py
omero_biomero/leica_file_browser/CreatePreview.py
omero_biomero/leica_file_browser/ParseLeicaImageXML.py
omero_biomero/leica_file_browser/ParseLeicaImageXMLLite.py
omero_biomero/leica_file_browser/ReadLeicaLIF.py
omero_biomero/leica_file_browser/ReadLeicaLOF.py
omero_biomero/leica_file_browser/ReadLeicaXLEF.py
omero_biomero/leica_file_browser/ci_leica_converters_helpers.py
omero_biomero/static/omero_biomero/assets/asset-manifest.json
omero_biomero/static/omero_biomero/assets/main.14619d69ed529fa1589a.js
omero_biomero/static/omero_biomero/assets/main.14619d69ed529fa1589a.js.map
omero_biomero/static/omero_biomero/assets/main.1c1cddc1b22d053d4b68.js
omero_biomero/static/omero_biomero/assets/main.1c1cddc1b22d053d4b68.js.LICENSE.txt
omero_biomero/static/omero_biomero/assets/main.1c1cddc1b22d053d4b68.js.map
omero_biomero/static/omero_biomero/assets/main.2402bf9c06063ed4b903.js
omero_biomero/static/omero_biomero/assets/main.2402bf9c06063ed4b903.js.map
omero_biomero/static/omero_biomero/assets/main.5785968435f5dc34d22a.js
omero_biomero/static/omero_biomero/assets/main.5785968435f5dc34d22a.js.map
omero_biomero/static/omero_biomero/assets/main.80e4d5fc6879df63daa6.js
omero_biomero/static/omero_biomero/assets/main.80e4d5fc6879df63daa6.js.map
omero_biomero/static/omero_biomero/assets/main.842384bb9fbdafbc9d23.js
omero_biomero/static/omero_biomero/assets/main.842384bb9fbdafbc9d23.js.map
omero_biomero/templates/omero_biomero/webclient_plugins/react_app.html
omero_biomero/tests/__init__.py
omero_biomero/tests/test_admin_views.py
omero_biomero/tests/test_analyzer_views.py
omero_biomero/tests/test_biomero_views.py
omero_biomero-1.1.0.dist-info/licenses/LICENSE
omero_biomero-1.1.0.dist-info/METADATA
omero_biomero-1.1.0.dist-info/WHEEL
omero_biomero-1.1.0.dist-info/entry_points.txt
omero_biomero-1.1.0.dist-info/top_level.txt
omero_biomero-1.1.0.dist-info/RECORD
