Metadata-Version: 2.4
Name: omero-biomero
Version: 1.1.0
Summary: A Python plugin for OMERO.web combining database pages, script menu, and web importer functionality
Home-page: https://github.com/NL-BioImaging/OMERO.biomero
Download-URL: https://github.com/NL-BioImaging/OMERO.biomero/archive/refs/tags/v{version}.tar.gz
Author: Cellular Imaging Amsterdam UMC
Author-email: cellularimaging@amsterdamumc.nl
License: AGPL-3.0
Keywords: OMERO.web,plugin,database pages,imports database,workflows database,script menu,web importer
Classifier: Development Status :: 3 - Alpha
Classifier: Environment :: Web Environment
Classifier: Framework :: Django
Classifier: Intended Audience :: Developers
Classifier: Natural Language :: English
Classifier: Operating System :: OS Independent
Classifier: Programming Language :: JavaScript
Classifier: Programming Language :: Python :: 3
Classifier: Topic :: Internet :: WWW/HTTP
Classifier: Topic :: Internet :: WWW/HTTP :: Dynamic Content
Classifier: Topic :: Internet :: WWW/HTTP :: WSGI
Classifier: Topic :: Scientific/Engineering :: Visualization
Classifier: Topic :: Software Development :: Libraries :: Application Frameworks
Requires-Python: >=3.12
License-File: LICENSE
Requires-Dist: omero-web>=5.6.0
Requires-Dist: pyjwt
Requires-Dist: biomero>=2.1.0
Requires-Dist: configupdater>=3.2
Requires-Dist: biomero-importer>=1.0.0
Dynamic: author
Dynamic: author-email
Dynamic: classifier
Dynamic: description
Dynamic: description-content-type
Dynamic: download-url
Dynamic: home-page
Dynamic: keywords
Dynamic: license
Dynamic: license-file
Dynamic: requires-dist
Dynamic: requires-python
Dynamic: summary
